[
    {
        "category": "Frontend",
        "item": ["html5", "css3", "javascript", "jquery", "react", "vuejs", "sass", "tailwindcss", "typescript", "webpack", "vitejs"
        ]
    },
    {
        "category": "Backend",
        "item": ["c", "cplusplus", "python", "rust", "go", "mysql", "sqlite", "cmake", "elasticsearch", "flask", "pytorch"
        ]
    },
    {
        "category": "Fullstack",
        "item": ["nodejs", "qt", "electron", "tauri", "cloudflareworkers", "jekyll"
        ]
    },
    {
        "category": "Tools",
        "item": ["linux", "windows8", "powershell", "git", "github", "githubactions", "vim", "vscode", "docker", "cloudflare", "jupyter", "postman"
        ]
    }
]